Metadata-Version: 1.0
Name: goose-extractor
Version: 1.0.23
Summary: Html Content / Article Extractor, web scrapping
Home-page: https://github.com/grangier/python-goose
Author: Xavier Grangier
Author-email: grangier@gmail.com
License: Apache
Keywords: scrapping,extractor,web scrapping
Platform: UNKNOWN
Classifier: Development Status :: 4 - Beta
Classifier: Environment :: Other Environment
Classifier: Intended Audience :: Developers
Classifier: License :: OSI Approved :: Apache Software License
Classifier: Operating System :: MacOS :: MacOS X
Classifier: Operating System :: POSIX
Classifier: Operating System :: Microsoft :: Windows
Classifier: Programming Language :: Python
Classifier: Programming Language :: Python
Classifier: Programming Language :: Python :: 2
Classifier: Programming Language :: Python :: 2.6
Classifier: Programming Language :: Python :: 2.7
Classifier: Topic :: Internet
Classifier: Topic :: Utilities
Classifier: Topic :: Software Development :: Libraries :: Python Modules
